gmscaffold/__init__.py
gmscaffold/__main__.py
gmscaffold/base/__init__.py
gmscaffold/base/command.py
gmscaffold/base/dataclass.py
gmscaffold/cmdline.py
gmscaffold/commands/GmAppCommand.py
gmscaffold/commands/SpiderCommand.py
gmscaffold/commands/WebCommand.py
gmscaffold/commands/__init__.py
gmscaffold/defer.py
gmscaffold/dispatcher.py
gmscaffold/entities/GmApp.py
gmscaffold/entities/__init__.py
gmscaffold/entities/project.py
gmscaffold/entities/spider.py
gmscaffold/entities/web.py
gmscaffold/exceptions.py
gmscaffold/extensions/GmApp.py
gmscaffold/extensions/__init__.py
gmscaffold/extensions/spider.py
gmscaffold/extensions/web.py
gmscaffold/icon/jm.jpg
gmscaffold/icon/jm.txt
gmscaffold/loader/__init__.py
gmscaffold/loader/process.py
gmscaffold/log.py
gmscaffold/settings/__init__.py
gmscaffold/settings/default_settings.py
gmscaffold/shell.py
gmscaffold/signalmanager.py
gmscaffold/templates/GmApp/.gitignore
gmscaffold/templates/GmApp/ReadMe.md
gmscaffold/templates/GmApp/app/__init__.tmpl
gmscaffold/templates/GmApp/app/consts/__init__.tmpl
gmscaffold/templates/GmApp/app/i18n/en.ini
gmscaffold/templates/GmApp/app/i18n/zh-CN.ini
gmscaffold/templates/GmApp/app/middlewares/__init__.tmpl
gmscaffold/templates/GmApp/app/middlewares/example.tmpl
gmscaffold/templates/GmApp/app/schemas/__init__.tmpl
gmscaffold/templates/GmApp/app/schemas/example.tmpl
gmscaffold/templates/GmApp/app/server.tmpl
gmscaffold/templates/GmApp/app/services/__init__.tmpl
gmscaffold/templates/GmApp/app/services/example.tmpl
gmscaffold/templates/GmApp/app/utils/__init__.tmpl
gmscaffold/templates/GmApp/build.sh
gmscaffold/templates/GmApp/config.yaml
gmscaffold/templates/GmApp/install.sh
gmscaffold/templates/GmApp/main.tmpl
gmscaffold/templates/GmApp/makefile
gmscaffold/templates/GmApp/requirements.txt
gmscaffold/templates/spider/ReadMe.md
gmscaffold/templates/spider/VERSION
gmscaffold/templates/spider/__init__.tmpl
gmscaffold/templates/spider/app/__init__.tmpl
gmscaffold-1.1.0.dist-info/LICENSE.txt
gmscaffold-1.1.0.dist-info/METADATA
gmscaffold-1.1.0.dist-info/WHEEL
gmscaffold-1.1.0.dist-info/entry_points.txt
gmscaffold-1.1.0.dist-info/RECORD
